opal_fetcher_dynamodb/__init__.py
opal_fetcher_dynamodb/provider.py
opal_fetcher_dynamodb-0.7.dist-info/LICENSE
opal_fetcher_dynamodb-0.7.dist-info/METADATA
opal_fetcher_dynamodb-0.7.dist-info/WHEEL
opal_fetcher_dynamodb-0.7.dist-info/top_level.txt
opal_fetcher_dynamodb-0.7.dist-info/RECORD
